minobot/__init__.py
minobot/assets/maze/end.png
minobot/assets/maze/key.png
minobot/assets/maze/leaf_0.png
minobot/assets/maze/leaf_1.png
minobot/assets/maze/leaf_2.png
minobot/assets/maze/leaf_3.png
minobot/assets/maze/leaf_4.png
minobot/assets/maze/leaf_5.png
minobot/assets/maze/leaf_6.png
minobot/assets/maze/leaf_7.png
minobot/assets/maze/lock.png
minobot/assets/maze/paint_0.png
minobot/assets/maze/paint_1.png
minobot/assets/maze/paint_2.png
minobot/assets/maze/paint_3.png
minobot/assets/maze/path_0.png
minobot/assets/maze/start.png
minobot/assets/maze/wall_0.png
minobot/assets/maze/wall_leaf_0.png
minobot/assets/maze/wall_leaf_1.png
minobot/assets/maze/wall_leaf_2.png
minobot/assets/maze/wall_leaf_3.png
minobot/assets/maze/wall_leaf_4.png
minobot/assets/maze/wall_leaf_5.png
minobot/assets/maze/wall_lock.png
minobot/assets/robot_humanlike/east.png
minobot/assets/robot_humanlike/north.png
minobot/assets/robot_humanlike/south.png
minobot/assets/robot_humanlike/west.png
minobot/assets/robot_robolike/east.png
minobot/assets/robot_robolike/north.png
minobot/assets/robot_robolike/south.png
minobot/assets/robot_robolike/west.png
minobot/base_visualizer.py
minobot/examples.py
minobot/instructions.py
minobot/maze.py
minobot/notebook_utils.py
minobot/pygame_visualizer.py
minobot/rendering_backend.py
minobot/robot.py
minobot/runner.py
minobot/sprite_assets.py
minobot/video_visualizer.py
minobot-0.0.6.dist-info/licenses/LICENSE
minobot-0.0.6.dist-info/WHEEL
minobot-0.0.6.dist-info/METADATA
minobot-0.0.6.dist-info/RECORD
