Metadata-Version: 2.4
Name: minobot
Version: 0.0.6
Summary: A package for visualizing maze solving intended for students learning programming with Python. Developed at the VU Amsterdam.
Keywords: maze,education
Author: Banno Postma, Ahmad Ramadan, Mauricio Verano Merino
Author-email: Banno Postma <b.postma@vu.nl>, Mauricio Verano Merino <m.verano.merino@vu.nl>
License-Expression: MIT
License-File: LICENSE
Classifier: Programming Language :: Python :: 3
Classifier: License :: OSI Approved :: MIT License
Classifier: Topic :: Education
Requires-Dist: pygame>=2.6.1
Requires-Dist: opencv-python>=4.8.0
Requires-Dist: matplotlib>=3.7.0
Requires-Dist: numpy>=1.24.0
Requires-Dist: ipykernel>=6.29.5
Requires-Python: >=3.10
